{
    "openx":{
        "BLOCK":{
            "mean":1.231850857142857,
            "std_dev":2.074575106101816,
            "median":0.43800000000000006,
            "less_than_10":false
        },
        "Health":{
            "mean":3.029206762589928,
            "std_dev":3.385148639195596,
            "median":0.9380000000000001,
            "less_than_10":false
        },
        "Arts":{
            "mean":1.5249847552447553,
            "std_dev":5.472985434188193,
            "median":0.36900000000000005,
            "less_than_10":false
        },
        "Science":{
            "mean":2.8263921782178216,
            "std_dev":11.868868776284685,
            "median":0.44462,
            "less_than_10":false
        },
        "Games":{
            "mean":1.004376690647482,
            "std_dev":1.6714094590311162,
            "median":0.343,
            "less_than_10":false
        },
        "Home":{
            "mean":1.1030875187969926,
            "std_dev":2.0599989741257416,
            "median":0.28200000000000003,
            "less_than_10":false
        },
        "Regional":{
            "mean":4.3402002469135805,
            "std_dev":15.580429019605743,
            "median":0.7260000000000001,
            "less_than_10":false
        },
        "Society":{
            "mean":1.1879836842105262,
            "std_dev":2.2043451287576667,
            "median":0.452,
            "less_than_10":false
        },
        "Shopping":{
            "mean":2.6188424096385536,
            "std_dev":20.836574245186867,
            "median":0.4661,
            "less_than_10":false
        },
        "Sports":{
            "mean":1.14905305785124,
            "std_dev":2.163596163823204,
            "median":0.232,
            "less_than_10":false
        },
        "Business":{
            "mean":1.8078635294117646,
            "std_dev":11.190879386818397,
            "median":0.29700000000000004,
            "less_than_10":false
        },
        "Computers":{
            "mean":2.2034019999999996,
            "std_dev":8.131998580282463,
            "median":0.547,
            "less_than_10":false
        },
        "Recreation":{
            "mean":3.04498625,
            "std_dev":11.816513405134566,
            "median":0.36300000000000004,
            "less_than_10":false
        },
        "Reference":{
            "mean":1.3476316666666668,
            "std_dev":5.208223873073505,
            "median":0.521,
            "less_than_10":false
        },
        "Kids_and_Teens":{
            "mean":1.8664124137931037,
            "std_dev":7.494824910230946,
            "median":0.4712,
            "less_than_10":false
        },
        "News":{
            "mean":1.6483126984126981,
            "std_dev":5.586320817129633,
            "median":0.41280000000000006,
            "less_than_10":false
        },
        "Adult":{
            "mean":1.0816384615384615,
            "std_dev":2.6389342102384563,
            "median":0.3355,
            "less_than_10":false
        }
    },
    "ix":{
        "BLOCK":{
            "mean":0.8633414201183431,
            "std_dev":2.210029514287992,
            "median":0.28,
            "less_than_10":false
        },
        "Recreation":{
            "mean":1.1213107142857142,
            "std_dev":2.3636669667125405,
            "median":0.27,
            "less_than_10":false
        },
        "Arts":{
            "mean":1.1079636363636365,
            "std_dev":3.161771709452918,
            "median":0.25,
            "less_than_10":false
        },
        "Science":{
            "mean":1.0789843065693432,
            "std_dev":3.470870548681213,
            "median":0.28,
            "less_than_10":false
        },
        "Games":{
            "mean":1.010602953586498,
            "std_dev":2.183418855665119,
            "median":0.2,
            "less_than_10":false
        },
        "Home":{
            "mean":0.8341029411764707,
            "std_dev":1.5762347574322704,
            "median":0.225,
            "less_than_10":false
        },
        "Regional":{
            "mean":0.8911207207207207,
            "std_dev":2.2184063615726823,
            "median":0.28,
            "less_than_10":false
        },
        "Adult":{
            "mean":1.0307531578947369,
            "std_dev":2.1645683426896545,
            "median":0.245,
            "less_than_10":false
        },
        "Society":{
            "mean":1.6372360730593607,
            "std_dev":2.962811162723505,
            "median":0.28,
            "less_than_10":false
        },
        "Shopping":{
            "mean":0.9242636363636364,
            "std_dev":1.7743163887294873,
            "median":0.39,
            "less_than_10":false
        },
        "Sports":{
            "mean":0.6279079812206572,
            "std_dev":1.2489764017745977,
            "median":0.13,
            "less_than_10":false
        },
        "Business":{
            "mean":0.7959978632478634,
            "std_dev":1.916234156717676,
            "median":0.29000000000000004,
            "less_than_10":false
        },
        "Computers":{
            "mean":0.9138652631578946,
            "std_dev":1.7383021585363976,
            "median":0.20750000000000002,
            "less_than_10":false
        },
        "Reference":{
            "mean":0.9083069868995634,
            "std_dev":2.756797002257192,
            "median":0.2,
            "less_than_10":false
        },
        "Kids_and_Teens":{
            "mean":0.8891884615384615,
            "std_dev":2.6718926805013834,
            "median":0.18,
            "less_than_10":false
        },
        "News":{
            "mean":0.9372091304347826,
            "std_dev":1.578690725984016,
            "median":0.2407,
            "less_than_10":false
        },
        "Health":{
            "mean":2.608576119402985,
            "std_dev":3.7278855622191323,
            "median":0.6700000000000002,
            "less_than_10":false
        }
    },
    "rubicon":{
        "BLOCK":{
            "mean":1.7796867904347824,
            "std_dev":3.7902733566159763,
            "median":0.263223,
            "less_than_10":false
        },
        "Recreation":{
            "mean":1.374218272900433,
            "std_dev":1.8678734915069566,
            "median":0.6739560000000001,
            "less_than_10":false
        },
        "Health":{
            "mean":2.261148677777778,
            "std_dev":3.038582169015692,
            "median":1.1604035000000001,
            "less_than_10":false
        },
        "Arts":{
            "mean":1.3031262501554401,
            "std_dev":2.0194925921487665,
            "median":0.44879648,
            "less_than_10":false
        },
        "Science":{
            "mean":1.5240277559148938,
            "std_dev":2.482773896788557,
            "median":0.7045368000000001,
            "less_than_10":false
        },
        "Games":{
            "mean":1.6725173395698927,
            "std_dev":3.203629627632091,
            "median":0.32536000000000004,
            "less_than_10":false
        },
        "Home":{
            "mean":1.5419333662921346,
            "std_dev":2.438086245357513,
            "median":0.39409000000000005,
            "less_than_10":false
        },
        "Regional":{
            "mean":1.527646250909091,
            "std_dev":2.457884813849443,
            "median":0.42791850000000003,
            "less_than_10":false
        },
        "Kids_and_Teens":{
            "mean":0.9945220741361257,
            "std_dev":1.4515159244117075,
            "median":0.40669,
            "less_than_10":false
        },
        "Adult":{
            "mean":1.2688188388304094,
            "std_dev":1.6852754703153583,
            "median":0.429999,
            "less_than_10":false
        },
        "Business":{
            "mean":1.286291195106383,
            "std_dev":2.2377999160484108,
            "median":0.44856000000000007,
            "less_than_10":false
        },
        "Society":{
            "mean":1.866752532694611,
            "std_dev":2.792377150512316,
            "median":0.406685,
            "less_than_10":false
        },
        "Shopping":{
            "mean":1.4617229689219329,
            "std_dev":2.068514394433099,
            "median":0.5636000000000001,
            "less_than_10":false
        },
        "Sports":{
            "mean":1.286954811898734,
            "std_dev":1.9531437631034252,
            "median":0.34667000000000003,
            "less_than_10":false
        },
        "Computers":{
            "mean":2.3449351991709846,
            "std_dev":3.7336962001788323,
            "median":0.7500000000000001,
            "less_than_10":false
        },
        "Reference":{
            "mean":1.249648874883721,
            "std_dev":2.027345637539416,
            "median":0.532435,
            "less_than_10":false
        },
        "News":{
            "mean":2.19883821173913,
            "std_dev":3.7429112151064383,
            "median":0.6081080000000001,
            "less_than_10":false
        }
    },
    "appnexus":{
        "BLOCK":{
            "mean":0.5708776880466473,
            "std_dev":0.9744462267208399,
            "median":0.17809700000000003,
            "less_than_10":false
        },
        "Adult":{
            "mean":0.6669089056603774,
            "std_dev":1.2887614292187175,
            "median":0.16068750000000004,
            "less_than_10":false
        },
        "Arts":{
            "mean":0.819733775280899,
            "std_dev":1.3622215281609988,
            "median":0.3197055000000001,
            "less_than_10":false
        },
        "Society":{
            "mean":0.8290942515337423,
            "std_dev":1.4080777066353949,
            "median":0.21309050000000002,
            "less_than_10":false
        },
        "Science":{
            "mean":0.842111193548387,
            "std_dev":1.4028256388805367,
            "median":0.2842565,
            "less_than_10":false
        },
        "Kids_and_Teens":{
            "mean":0.7391678011869435,
            "std_dev":1.3449995931564955,
            "median":0.14804000000000003,
            "less_than_10":false
        },
        "News":{
            "mean":0.7283142000000001,
            "std_dev":1.4229439407297044,
            "median":0.1905195,
            "less_than_10":false
        },
        "Games":{
            "mean":0.6814759522471909,
            "std_dev":1.3266855639652857,
            "median":0.21000000000000002,
            "less_than_10":false
        },
        "Business":{
            "mean":0.8386995341614906,
            "std_dev":1.475678070757395,
            "median":0.2805,
            "less_than_10":false
        },
        "Home":{
            "mean":0.7137979363395225,
            "std_dev":1.3745007374408686,
            "median":0.20240000000000002,
            "less_than_10":false
        },
        "Regional":{
            "mean":1.2781622679045093,
            "std_dev":2.4360305842250654,
            "median":0.21590300000000004,
            "less_than_10":false
        },
        "Shopping":{
            "mean":0.9721125014245016,
            "std_dev":1.4552571592591996,
            "median":0.42140000000000005,
            "less_than_10":false
        },
        "Recreation":{
            "mean":0.7533572773109244,
            "std_dev":1.1808829346244432,
            "median":0.292895,
            "less_than_10":false
        },
        "Health":{
            "mean":0.9984387718309861,
            "std_dev":1.7367242504429306,
            "median":0.195352,
            "less_than_10":false
        },
        "Sports":{
            "mean":0.7267726017964072,
            "std_dev":1.3751499967327008,
            "median":0.17,
            "less_than_10":false
        },
        "Reference":{
            "mean":0.642877861356932,
            "std_dev":1.1365550649884233,
            "median":0.17292800000000003,
            "less_than_10":false
        },
        "Computers":{
            "mean":0.8744625545722714,
            "std_dev":1.5175990656080491,
            "median":0.19673500000000002,
            "less_than_10":false
        }
    },
    "lockerdome":{
        "Health":{
            "mean":0.10250000000000002,
            "std_dev":0.03467107343785787,
            "median":0.115,
            "less_than_10":false
        },
        "Games":{
            "mean":0.10250000000000002,
            "std_dev":0.03467107343785787,
            "median":0.115,
            "less_than_10":false
        },
        "Regional":{
            "mean":0.10250000000000002,
            "std_dev":0.03467107343785787,
            "median":0.115,
            "less_than_10":false
        },
        "BLOCK":{
            "mean":0.10250000000000002,
            "std_dev":0.03467107343785787,
            "median":0.115,
            "less_than_10":false
        },
        "Computers":{
            "mean":0.095,
            "std_dev":0.03201562118716425,
            "median":0.1,
            "less_than_10":true
        },
        "Shopping":{
            "mean":0.10250000000000002,
            "std_dev":0.03467107343785787,
            "median":0.115,
            "less_than_10":false
        },
        "Recreation":{
            "mean":0.10250000000000002,
            "std_dev":0.03467107343785787,
            "median":0.115,
            "less_than_10":false
        },
        "Adult":{
            "mean":0.10250000000000002,
            "std_dev":0.03467107343785787,
            "median":0.115,
            "less_than_10":false
        },
        "Reference":{
            "mean":0.10250000000000002,
            "std_dev":0.03467107343785787,
            "median":0.115,
            "less_than_10":false
        },
        "Kids_and_Teens":{
            "mean":0.10250000000000002,
            "std_dev":0.03467107343785787,
            "median":0.115,
            "less_than_10":false
        },
        "Society":{
            "mean":0.10250000000000002,
            "std_dev":0.03467107343785787,
            "median":0.115,
            "less_than_10":false
        },
        "Home":{
            "mean":0.10250000000000002,
            "std_dev":0.03467107343785787,
            "median":0.115,
            "less_than_10":false
        },
        "Arts":{
            "mean":0.10250000000000002,
            "std_dev":0.03467107343785787,
            "median":0.115,
            "less_than_10":false
        },
        "Science":{
            "mean":0.10250000000000002,
            "std_dev":0.03467107343785787,
            "median":0.115,
            "less_than_10":false
        },
        "Business":{
            "mean":0.10250000000000002,
            "std_dev":0.03467107343785787,
            "median":0.115,
            "less_than_10":false
        },
        "Sports":{
            "mean":0.10250000000000002,
            "std_dev":0.03467107343785787,
            "median":0.115,
            "less_than_10":false
        },
        "News":{
            "mean":0.10250000000000002,
            "std_dev":0.03467107343785787,
            "median":0.115,
            "less_than_10":false
        }
    },
    "pubmatic":{
        "Society":{
            "mean":1.8650789915966386,
            "std_dev":4.607162585353156,
            "median":0.37000000000000005,
            "less_than_10":false
        },
        "Science":{
            "mean":1.990594581280788,
            "std_dev":6.616253597715326,
            "median":0.58,
            "less_than_10":false
        },
        "Games":{
            "mean":0.9091715328467154,
            "std_dev":2.935045369150304,
            "median":0.25,
            "less_than_10":false
        },
        "Business":{
            "mean":1.0401269461077842,
            "std_dev":3.1308702297255455,
            "median":0.51,
            "less_than_10":false
        },
        "Recreation":{
            "mean":3.2798083333333325,
            "std_dev":18.293937405662632,
            "median":0.43500000000000005,
            "less_than_10":false
        },
        "Adult":{
            "mean":1.598215517241379,
            "std_dev":5.145233654501454,
            "median":0.32500000000000007,
            "less_than_10":false
        },
        "Arts":{
            "mean":1.6918923076923074,
            "std_dev":5.0942838783002715,
            "median":0.35500000000000004,
            "less_than_10":false
        },
        "Sports":{
            "mean":1.3056945736434107,
            "std_dev":3.842293511144679,
            "median":0.30000000000000004,
            "less_than_10":false
        },
        "Home":{
            "mean":1.3692149659863948,
            "std_dev":4.104090753799466,
            "median":0.28,
            "less_than_10":false
        },
        "Regional":{
            "mean":1.4531119496855347,
            "std_dev":3.7419356660659866,
            "median":0.35000000000000003,
            "less_than_10":false
        },
        "Health":{
            "mean":2.442280701754386,
            "std_dev":4.316335901793669,
            "median":0.54,
            "less_than_10":false
        },
        "Shopping":{
            "mean":1.1420833333333336,
            "std_dev":2.0602831099282337,
            "median":0.6000000000000001,
            "less_than_10":false
        },
        "News":{
            "mean":1.7043657407407407,
            "std_dev":5.402315638312513,
            "median":0.32500000000000007,
            "less_than_10":false
        },
        "BLOCK":{
            "mean":1.0136229007633586,
            "std_dev":3.3286398177208616,
            "median":0.37000000000000005,
            "less_than_10":false
        },
        "Reference":{
            "mean":2.194490825688073,
            "std_dev":7.436729645242564,
            "median":0.58,
            "less_than_10":false
        },
        "Kids_and_Teens":{
            "mean":1.89401484375,
            "std_dev":7.343314992425613,
            "median":0.29500000000000004,
            "less_than_10":false
        },
        "Computers":{
            "mean":5.521480985915493,
            "std_dev":41.84847519733163,
            "median":0.7300000000000001,
            "less_than_10":false
        }
    },
    "districtm":{
        "Science":{
            "mean":1.7006052083333332,
            "std_dev":1.776038085524315,
            "median":1.3146355,
            "less_than_10":false
        },
        "Regional":{
            "mean":3.7283035777777793,
            "std_dev":3.565402405156899,
            "median":2.136614,
            "less_than_10":false
        },
        "Arts":{
            "mean":3.2019773636363635,
            "std_dev":2.881474168239918,
            "median":2.191503,
            "less_than_10":false
        },
        "Home":{
            "mean":1.722637351351351,
            "std_dev":1.9871847660833235,
            "median":1.130467,
            "less_than_10":false
        },
        "Society":{
            "mean":2.6596568620689656,
            "std_dev":2.99988344194785,
            "median":1.184625,
            "less_than_10":false
        },
        "Business":{
            "mean":1.8853668571428568,
            "std_dev":2.1428913841003054,
            "median":1.272375,
            "less_than_10":false
        },
        "Reference":{
            "mean":2.3317953749999996,
            "std_dev":2.178532974414445,
            "median":1.331658,
            "less_than_10":false
        },
        "News":{
            "mean":2.71547384,
            "std_dev":2.773610061828803,
            "median":1.5093699999999999,
            "less_than_10":false
        },
        "Sports":{
            "mean":2.7931162692307696,
            "std_dev":2.8983168343141923,
            "median":1.892904,
            "less_than_10":false
        },
        "Health":{
            "mean":1.9874440731707315,
            "std_dev":1.5529852357165315,
            "median":1.892904,
            "less_than_10":false
        },
        "Shopping":{
            "mean":1.4021814285714287,
            "std_dev":1.6569116443954819,
            "median":1.0610024999999998,
            "less_than_10":false
        },
        "Computers":{
            "mean":1.7878919999999996,
            "std_dev":2.032634324902484,
            "median":1.096875,
            "less_than_10":false
        },
        "Recreation":{
            "mean":2.5077998918918913,
            "std_dev":2.6910609570821364,
            "median":1.356984,
            "less_than_10":false
        },
        "BLOCK":{
            "mean":2.886139750000001,
            "std_dev":3.304668867886265,
            "median":1.354714,
            "less_than_10":false
        },
        "Kids_and_Teens":{
            "mean":2.0389234411764705,
            "std_dev":1.9363301758267486,
            "median":1.4211099999999999,
            "less_than_10":false
        },
        "Adult":{
            "mean":2.25054696875,
            "std_dev":2.4172912993027116,
            "median":1.3164825,
            "less_than_10":false
        },
        "Games":{
            "mean":3.7799115666666663,
            "std_dev":3.333152007912947,
            "median":2.2620885,
            "less_than_10":false
        }
    },
    "conversant":{
        "Science":{
            "mean":0.23000000000000004,
            "std_dev":0.09797958971132714,
            "median":0.25,
            "less_than_10":true
        },
        "Home":{
            "mean":0.25,
            "std_dev":0.0,
            "median":0.25,
            "less_than_10":true
        },
        "Reference":{
            "mean":0.15,
            "std_dev":0.1,
            "median":0.15,
            "less_than_10":true
        },
        "News":{
            "mean":0.31666666666666665,
            "std_dev":0.09428090415820634,
            "median":0.25,
            "less_than_10":true
        },
        "Health":{
            "mean":0.20171666666666668,
            "std_dev":0.09617814056334331,
            "median":0.21625,
            "less_than_10":true
        },
        "Shopping":{
            "mean":3.0068571428571427,
            "std_dev":3.181511564765197,
            "median":2.38,
            "less_than_10":false
        },
        "Adult":{
            "mean":0.35,
            "std_dev":0.1224744871391589,
            "median":0.25,
            "less_than_10":true
        },
        "Computers":{
            "mean":0.21666666666666667,
            "std_dev":0.12472191289246473,
            "median":0.25,
            "less_than_10":true
        },
        "BLOCK":{
            "mean":0.2,
            "std_dev":0.08660254037844387,
            "median":0.25,
            "less_than_10":true
        },
        "Sports":{
            "mean":0.25,
            "std_dev":0.0,
            "median":0.25,
            "less_than_10":true
        },
        "Regional":{
            "mean":1.4560000000000002,
            "std_dev":0.7680781210267613,
            "median":1.61,
            "less_than_10":true
        },
        "Society":{
            "mean":0.21625,
            "std_dev":0.03375,
            "median":0.21625,
            "less_than_10":true
        },
        "Kids_and_Teens":{
            "mean":0.35000000000000003,
            "std_dev":0.18371173070873836,
            "median":0.42500000000000004,
            "less_than_10":true
        },
        "Recreation":{
            "mean":0.3551428571428571,
            "std_dev":0.1759508280104161,
            "median":0.5,
            "less_than_10":true
        },
        "Business":{
            "mean":0.8475,
            "std_dev":0.773639935628972,
            "median":0.5,
            "less_than_10":true
        },
        "Games":{
            "mean":0.25,
            "std_dev":0.0,
            "median":0.25,
            "less_than_10":true
        },
        "Arts":{
            "mean":0.551825,
            "std_dev":0.29818616982516144,
            "median":0.5536500000000001,
            "less_than_10":true
        }
    },
    "sovrn":{
        "Games":{
            "mean":0.2057204497634726,
            "std_dev":0.5002612194565549,
            "median":0.08938684865832326,
            "less_than_10":false
        },
        "Shopping":{
            "mean":0.10819566638643544,
            "std_dev":0.1347613125169559,
            "median":0.05432173572480678,
            "less_than_10":false
        },
        "Reference":{
            "mean":0.19861803897915384,
            "std_dev":0.37134885578690957,
            "median":0.11086408987641336,
            "less_than_10":false
        },
        "Kids_and_Teens":{
            "mean":0.23080028612794484,
            "std_dev":0.48086989680723574,
            "median":0.09983040675520896,
            "less_than_10":false
        },
        "Society":{
            "mean":0.2613342877016925,
            "std_dev":0.4036300682437346,
            "median":0.07216983295977115,
            "less_than_10":false
        },
        "Home":{
            "mean":0.1835670548654053,
            "std_dev":0.23777660149026225,
            "median":0.11208369478583335,
            "less_than_10":false
        },
        "Arts":{
            "mean":0.27311625372002707,
            "std_dev":0.668089755021637,
            "median":0.06885680176317692,
            "less_than_10":false
        },
        "Business":{
            "mean":0.16377595455532687,
            "std_dev":0.3263944844250528,
            "median":0.06977606922388077,
            "less_than_10":false
        },
        "Sports":{
            "mean":0.15800023794891174,
            "std_dev":0.3262839761748571,
            "median":0.0655719942599535,
            "less_than_10":false
        },
        "News":{
            "mean":0.3297074185421928,
            "std_dev":0.7894694448734193,
            "median":0.08287297297269106,
            "less_than_10":false
        },
        "Health":{
            "mean":0.6346247721240752,
            "std_dev":1.2846471698416642,
            "median":0.05332999045029282,
            "less_than_10":false
        },
        "Adult":{
            "mean":0.24006424190796474,
            "std_dev":0.7254324095593121,
            "median":0.043301929458975805,
            "less_than_10":false
        },
        "Recreation":{
            "mean":0.4694459312290708,
            "std_dev":1.2703921041036736,
            "median":0.11943621426820755,
            "less_than_10":false
        },
        "Science":{
            "mean":0.3361683365226018,
            "std_dev":0.44412598864566727,
            "median":0.11943621426820755,
            "less_than_10":false
        },
        "Regional":{
            "mean":0.4493883165314084,
            "std_dev":1.3776849960047388,
            "median":0.06579244084656241,
            "less_than_10":false
        },
        "BLOCK":{
            "mean":0.06304460740702994,
            "std_dev":0.031589242565888596,
            "median":0.06294553965330123,
            "less_than_10":false
        },
        "Computers":{
            "mean":0.5086402843677997,
            "std_dev":1.39046831243894,
            "median":0.06294553965330123,
            "less_than_10":false
        }
    },
    "aol":{
        "Games":{
            "mean":0.3547418507462686,
            "std_dev":0.7224527797262094,
            "median":0.15300000000000002,
            "less_than_10":false
        },
        "Kids_and_Teens":{
            "mean":0.7623663333333334,
            "std_dev":1.3444640093333764,
            "median":0.225,
            "less_than_10":false
        },
        "Regional":{
            "mean":0.3596881846153846,
            "std_dev":0.7739453929045917,
            "median":0.13,
            "less_than_10":false
        },
        "BLOCK":{
            "mean":0.40569968,
            "std_dev":0.6335267969494405,
            "median":0.18,
            "less_than_10":false
        },
        "Business":{
            "mean":0.5246732698412699,
            "std_dev":0.8040888177440292,
            "median":0.2635,
            "less_than_10":false
        },
        "Computers":{
            "mean":0.5746314418604652,
            "std_dev":0.9584439826323464,
            "median":0.26175000000000004,
            "less_than_10":false
        },
        "Health":{
            "mean":0.8120573103448275,
            "std_dev":1.1584301559547376,
            "median":0.27,
            "less_than_10":false
        },
        "Recreation":{
            "mean":1.481643157894737,
            "std_dev":2.706225283919164,
            "median":0.2805,
            "less_than_10":false
        },
        "Shopping":{
            "mean":0.6126145507246377,
            "std_dev":0.9725222352059995,
            "median":0.23,
            "less_than_10":false
        },
        "Reference":{
            "mean":0.43904085393258435,
            "std_dev":0.749571040189445,
            "median":0.15300000000000002,
            "less_than_10":false
        },
        "Society":{
            "mean":0.4122145454545454,
            "std_dev":0.8241261605238893,
            "median":0.18,
            "less_than_10":false
        },
        "Science":{
            "mean":0.634967493670886,
            "std_dev":0.9582243204825792,
            "median":0.24650000000000002,
            "less_than_10":false
        },
        "Home":{
            "mean":0.30019929670329676,
            "std_dev":0.6398334315476949,
            "median":0.16,
            "less_than_10":false
        },
        "Arts":{
            "mean":0.22656175000000003,
            "std_dev":0.3153044907972886,
            "median":0.15300000000000002,
            "less_than_10":false
        },
        "Sports":{
            "mean":0.4032348888888889,
            "std_dev":0.8619045774807793,
            "median":0.15300000000000002,
            "less_than_10":false
        },
        "News":{
            "mean":0.7235767816091955,
            "std_dev":1.7128620997192545,
            "median":0.25,
            "less_than_10":false
        },
        "Adult":{
            "mean":0.6073375000000001,
            "std_dev":1.468781911940554,
            "median":0.22,
            "less_than_10":false
        }
    },
    "criteo":{
        "Regional":{
            "mean":0.6876782464678399,
            "std_dev":3.815916252065581,
            "median":0.05384085513651371,
            "less_than_10":false
        },
        "Sports":{
            "mean":0.07206752969593298,
            "std_dev":0.09510573236538612,
            "median":0.049930680543184294,
            "less_than_10":false
        },
        "Shopping":{
            "mean":2.4634202742889593,
            "std_dev":19.201307171139362,
            "median":0.364354968070984,
            "less_than_10":false
        },
        "Home":{
            "mean":0.4117530401663732,
            "std_dev":4.140005940670353,
            "median":0.07006402313709259,
            "less_than_10":false
        },
        "Science":{
            "mean":3.491560170904326,
            "std_dev":22.56928827256021,
            "median":0.2351629585027695,
            "less_than_10":false
        },
        "Games":{
            "mean":0.05417011273295983,
            "std_dev":0.017869753415249958,
            "median":0.046197336167097085,
            "less_than_10":false
        },
        "Recreation":{
            "mean":0.6832986554715055,
            "std_dev":3.8785270725977177,
            "median":0.05989555269479752,
            "less_than_10":false
        },
        "Business":{
            "mean":2.1090657473772976,
            "std_dev":16.106582306101714,
            "median":0.1629580557346344,
            "less_than_10":false
        },
        "Arts":{
            "mean":1.6675028673952486,
            "std_dev":9.80559293168525,
            "median":0.06819581985473633,
            "less_than_10":false
        },
        "Society":{
            "mean":0.07240535221669987,
            "std_dev":0.0911082755260299,
            "median":0.04076604172587395,
            "less_than_10":false
        },
        "Reference":{
            "mean":0.044475338421762003,
            "std_dev":0.005923017947915421,
            "median":0.04036523215472699,
            "less_than_10":false
        },
        "Computers":{
            "mean":0.22146378101452313,
            "std_dev":1.0934643190102007,
            "median":0.051002841442823424,
            "less_than_10":false
        },
        "BLOCK":{
            "mean":0.04000113159418107,
            "std_dev":0.0,
            "median":0.04000113159418107,
            "less_than_10":true
        },
        "Kids_and_Teens":{
            "mean":0.066374060855462,
            "std_dev":0.1273585139786225,
            "median":0.044408407062292085,
            "less_than_10":false
        },
        "News":{
            "mean":0.04876625703440772,
            "std_dev":0.005394988967789953,
            "median":0.04576890543103217,
            "less_than_10":true
        }
    },
    "triplelift":{
        "BLOCK":{
            "mean":0.9130222222222222,
            "std_dev":0.7313989408095175,
            "median":0.6260000000000001,
            "less_than_10":true
        },
        "Kids_and_Teens":{
            "mean":1.03015375,
            "std_dev":0.8642107871265768,
            "median":0.67473,
            "less_than_10":false
        },
        "Reference":{
            "mean":0.8947240909090909,
            "std_dev":1.150052050010461,
            "median":0.538,
            "less_than_10":false
        },
        "Sports":{
            "mean":1.546919090909091,
            "std_dev":1.7325379233968488,
            "median":0.68208,
            "less_than_10":false
        },
        "Society":{
            "mean":0.9553200000000001,
            "std_dev":1.1106238936141553,
            "median":0.5225,
            "less_than_10":false
        },
        "Recreation":{
            "mean":1.0251907142857144,
            "std_dev":1.3929005553595413,
            "median":0.543,
            "less_than_10":false
        },
        "Business":{
            "mean":1.5772433333333333,
            "std_dev":1.3149413075561436,
            "median":1.2049999999999998,
            "less_than_10":false
        },
        "Health":{
            "mean":0.6989708333333332,
            "std_dev":0.37793460658907496,
            "median":0.543,
            "less_than_10":false
        },
        "Science":{
            "mean":0.8787142857142858,
            "std_dev":0.6797250944916133,
            "median":0.5690000000000001,
            "less_than_10":false
        },
        "Arts":{
            "mean":1.08677,
            "std_dev":1.2853567761464966,
            "median":0.517,
            "less_than_10":false
        },
        "Computers":{
            "mean":0.575875,
            "std_dev":0.30603081442070507,
            "median":0.513,
            "less_than_10":true
        },
        "Shopping":{
            "mean":0.8662326666666668,
            "std_dev":1.0905265040121161,
            "median":0.535,
            "less_than_10":false
        },
        "Regional":{
            "mean":1.5024057142857143,
            "std_dev":1.1258315167892212,
            "median":1.1223,
            "less_than_10":true
        },
        "News":{
            "mean":0.7764800000000001,
            "std_dev":0.3182510355049925,
            "median":0.7133999999999999,
            "less_than_10":true
        },
        "Home":{
            "mean":1.4489150000000002,
            "std_dev":0.6580850000000001,
            "median":1.4489150000000002,
            "less_than_10":true
        },
        "Games":{
            "mean":0.8248000000000001,
            "std_dev":0.6164558053907838,
            "median":0.41200000000000003,
            "less_than_10":true
        },
        "Adult":{
            "mean":0.6403333333333334,
            "std_dev":0.38285230688724975,
            "median":0.5305,
            "less_than_10":true
        }
    },
    "sonobi":{
        "Arts":{
            "mean":0.8469333333333334,
            "std_dev":0.16126213304913076,
            "median":0.9408000000000002,
            "less_than_10":true
        },
        "News":{
            "mean":2.345,
            "std_dev":1.120829306064636,
            "median":2.17,
            "less_than_10":true
        },
        "Sports":{
            "mean":0.98,
            "std_dev":0.0,
            "median":0.98,
            "less_than_10":true
        },
        "Games":{
            "mean":0.4433333333333334,
            "std_dev":0.21699974398346397,
            "median":0.30000000000000004,
            "less_than_10":true
        },
        "Computers":{
            "mean":0.625,
            "std_dev":0.03500000000000009,
            "median":0.625,
            "less_than_10":true
        },
        "Regional":{
            "mean":2.455,
            "std_dev":0.5349999999999999,
            "median":2.455,
            "less_than_10":true
        },
        "Health":{
            "mean":0.7675,
            "std_dev":0.2685493436968335,
            "median":0.625,
            "less_than_10":true
        },
        "Shopping":{
            "mean":2.02,
            "std_dev":0.0,
            "median":2.02,
            "less_than_10":true
        },
        "Home":{
            "mean":1.42635,
            "std_dev":0.7551498245381508,
            "median":1.005,
            "less_than_10":true
        },
        "Kids_and_Teens":{
            "mean":2.17,
            "std_dev":0.0,
            "median":2.17,
            "less_than_10":true
        },
        "Recreation":{
            "mean":0.5,
            "std_dev":0.0,
            "median":0.5,
            "less_than_10":true
        },
        "Reference":{
            "mean":0.935,
            "std_dev":0.675,
            "median":0.935,
            "less_than_10":true
        },
        "Adult":{
            "mean":0.28500000000000003,
            "std_dev":0.0050000000000000044,
            "median":0.28500000000000003,
            "less_than_10":true
        },
        "Science":{
            "mean":1.0133333333333334,
            "std_dev":0.012472191289246483,
            "median":1.01,
            "less_than_10":true
        },
        "Society":{
            "mean":0.26,
            "std_dev":0.0,
            "median":0.26,
            "less_than_10":true
        },
        "Business":{
            "mean":0.9408000000000002,
            "std_dev":0.0,
            "median":0.9408000000000002,
            "less_than_10":true
        },
        "BLOCK":{
            "mean":0.7578000000000001,
            "std_dev":0.15780000000000005,
            "median":0.7578000000000001,
            "less_than_10":true
        }
    },
    "33across":{
        "Reference":{
            "mean":5.445445066666667,
            "std_dev":4.531173056711107,
            "median":3.9823399999999998,
            "less_than_10":true
        },
        "Regional":{
            "mean":4.3959216,
            "std_dev":4.254301578559,
            "median":2.5579576,
            "less_than_10":true
        },
        "Home":{
            "mean":3.69818784,
            "std_dev":2.929054663516258,
            "median":3.4862048000000003,
            "less_than_10":true
        },
        "Arts":{
            "mean":1.83576464,
            "std_dev":1.0820596860353644,
            "median":1.8087400000000002,
            "less_than_10":true
        },
        "News":{
            "mean":5.998988799999999,
            "std_dev":5.4234633030579085,
            "median":4.820110399999999,
            "less_than_10":true
        },
        "Sports":{
            "mean":4.525312700000001,
            "std_dev":1.6862885673249375,
            "median":5.1520308,
            "less_than_10":true
        },
        "Games":{
            "mean":4.6860051,
            "std_dev":4.387351786895744,
            "median":2.7922396,
            "less_than_10":true
        },
        "BLOCK":{
            "mean":3.530866285714285,
            "std_dev":1.4442840394603782,
            "median":3.7999104000000004,
            "less_than_10":true
        },
        "Business":{
            "mean":2.1182952,
            "std_dev":0.0,
            "median":2.1182952,
            "less_than_10":true
        },
        "Society":{
            "mean":3.5797211692307687,
            "std_dev":2.306822232572222,
            "median":3.4862048000000003,
            "less_than_10":false
        },
        "Shopping":{
            "mean":0.7119400000000002,
            "std_dev":0.10792590050585638,
            "median":0.7759400000000002,
            "less_than_10":true
        },
        "Computers":{
            "mean":7.919126499999999,
            "std_dev":3.771543377490957,
            "median":5.9946204000000005,
            "less_than_10":true
        },
        "Kids_and_Teens":{
            "mean":7.622973599999999,
            "std_dev":5.195620339434856,
            "median":5.949540000000001,
            "less_than_10":true
        },
        "Recreation":{
            "mean":2.3952845333333332,
            "std_dev":1.038150738176833,
            "median":2.0964335999999997,
            "less_than_10":true
        },
        "Science":{
            "mean":1.6482241600000003,
            "std_dev":1.1345223804482476,
            "median":1.2215399999999998,
            "less_than_10":true
        },
        "Adult":{
            "mean":2.6438048000000003,
            "std_dev":1.0308162153425409,
            "median":2.58754,
            "less_than_10":true
        }
    },
    "smartadserver":{
        "Business":{
            "mean":0.35304770999999996,
            "std_dev":0.35163897058780746,
            "median":0.1433221,
            "less_than_10":true
        },
        "Adult":{
            "mean":0.37093281850000004,
            "std_dev":0.21323042715230556,
            "median":0.252938926,
            "less_than_10":true
        },
        "Games":{
            "mean":0.679988705,
            "std_dev":0.32011870499999995,
            "median":0.6799887050000001,
            "less_than_10":true
        },
        "News":{
            "mean":0.9998026999999999,
            "std_dev":0.0,
            "median":0.9998026999999999,
            "less_than_10":true
        },
        "Society":{
            "mean":0.6707307276,
            "std_dev":0.477290397473515,
            "median":0.6011533,
            "less_than_10":true
        },
        "Home":{
            "mean":0.21049000000000004,
            "std_dev":0.0,
            "median":0.21049000000000004,
            "less_than_10":true
        },
        "Arts":{
            "mean":0.8730741283333332,
            "std_dev":0.5661111470094367,
            "median":0.5975212449999999,
            "less_than_10":true
        },
        "BLOCK":{
            "mean":0.546333615,
            "std_dev":0.453684625,
            "median":0.546333615,
            "less_than_10":true
        },
        "Regional":{
            "mean":0.8301200822499999,
            "std_dev":0.5591194337210142,
            "median":0.7240795945,
            "less_than_10":true
        },
        "Sports":{
            "mean":0.4169566666666667,
            "std_dev":0.08073273823067205,
            "median":0.3598700000000001,
            "less_than_10":true
        },
        "Reference":{
            "mean":0.98298738,
            "std_dev":0.7011588714829913,
            "median":1.01085057,
            "less_than_10":true
        }
    },
    "trustx":{
        "Computers":{
            "mean":1.7500000000000002,
            "std_dev":0.0,
            "median":1.7500000000000002,
            "less_than_10":true
        },
        "BLOCK":{
            "mean":1.7500000000000002,
            "std_dev":0.0,
            "median":1.7500000000000002,
            "less_than_10":true
        },
        "Kids_and_Teens":{
            "mean":1.3475,
            "std_dev":0.0,
            "median":1.3475,
            "less_than_10":true
        },
        "News":{
            "mean":1.3398849628700695,
            "std_dev":0.8823607361004734,
            "median":0.76575625,
            "less_than_10":true
        },
        "Home":{
            "mean":1.1832041666666668,
            "std_dev":0.3248289558453119,
            "median":1.4063875000000001,
            "less_than_10":true
        },
        "Society":{
            "mean":0.6309807230702746,
            "std_dev":0.17181427692972556,
            "median":0.6309807230702746,
            "less_than_10":true
        },
        "Games":{
            "mean":0.8027950000000001,
            "std_dev":0.0,
            "median":0.8027950000000001,
            "less_than_10":true
        },
        "Recreation":{
            "mean":0.539,
            "std_dev":0.0,
            "median":0.539,
            "less_than_10":true
        },
        "Business":{
            "mean":7.42616875,
            "std_dev":0.1340937499999999,
            "median":7.42616875,
            "less_than_10":true
        },
        "Health":{
            "mean":1.4437499999999996,
            "std_dev":0.0,
            "median":1.4437499999999996,
            "less_than_10":true
        },
        "Reference":{
            "mean":1.2604374999999999,
            "std_dev":0.0,
            "median":1.2604374999999999,
            "less_than_10":true
        }
    },
    "newsconnect":{
        "Business":{
            "mean":14.975000000000001,
            "std_dev":0.0,
            "median":14.975000000000001,
            "less_than_10":true
        }
    }
}